[
  {
    "name": "Bluetooth",
    "category": "Electronic",
    "value": "black",
    "quantity": 5,
    "price": "$30"
  },
  {
    "name": "Edifier M43560",
    "category": "Electronic",
    "value": "black",
    "quantity": 0,
    "price": "$30"
  },
  {
    "name": "Sony 4k ultra 55 inch TV",
    "category": "Electronic",
    "value": "black",
    "quantity": 17,
    "price": "$30"
  },
  {
    "name": "Samsumg 55 inch TV",
    "category": "Electronic",
    "value": "black",
    "quantity": 50,
    "price": "$30"
  },
  {
    "name": "samsumg S34 Ultra",
    "category": "phone",
    "value": "black",
    "quantity": 0,
    "price": "$30"
  }
]
